noorm/__init__.py
noorm/_common.py
noorm/_db_api_2.py
noorm/_db_api_2_args_only.py
noorm/_sqlalchemy_common.py
noorm/_sqlite_common.py
noorm/aiomysql/__init__.py
noorm/aiomysql/_aiomysql.py
noorm/aiosqlite/__init__.py
noorm/aiosqlite/_aiosqlite.py
noorm/asyncpg/__init__.py
noorm/asyncpg/_asyncpg.py
noorm/psycopg2/__init__.py
noorm/psycopg2/_psycopg2.py
noorm/py.typed
noorm/pymysql/__init__.py
noorm/pymysql/_pymysql.py
noorm/registry.py
noorm/sqlalchemy_async/__init__.py
noorm/sqlalchemy_async/_sqlalchemy_async.py
noorm/sqlalchemy_sync/__init__.py
noorm/sqlalchemy_sync/_sqlalchemy_sync.py
noorm/sqlite3/__init__.py
noorm/sqlite3/_sqlite3.py
true_noorm-0.1.7.dist-info/WHEEL
true_noorm-0.1.7.dist-info/METADATA
true_noorm-0.1.7.dist-info/LICENSE
true_noorm-0.1.7.dist-info/RECORD
