Metadata-Version: 2.1
Name: true-noorm
Version: 0.1.7
Summary: NoORM (Not only ORM) - make your database operations convenient and natural
Home-page: https://github.com/amaslyaev/noorm/
License: MIT
Keywords: database,sql,orm,noorm,sqlite,postgres,postgresql,mysql
Author: Alexander Maslyeav
Author-email: maslyaev@gmail.com
Requires-Python: >=3.10,<4.0
Classifier: Development Status :: 4 - Beta
Classifier: Intended Audience :: Developers
Classifier: License :: OSI Approved :: MIT License
Classifier: Programming Language :: Python :: 3
Classifier: Programming Language :: Python :: 3.10
Classifier: Programming Language :: Python :: 3.11
Classifier: Programming Language :: Python :: 3
Classifier: Programming Language :: Python :: 3.10
Classifier: Programming Language :: Python :: 3.11
Classifier: Programming Language :: Python :: 3.12
Classifier: Programming Language :: Python :: 3.13
Classifier: Topic :: Database
Classifier: Topic :: Software Development :: Libraries :: Python Modules
Project-URL: Repository, https://github.com/amaslyaev/noorm/
